core/__init__.py
core/args.py
core/checkpoint.py
core/distributed.py
core/logger.py
core/metrics.py
core/optim.py
core/probe.py
core/profiling.py
core/stool.py
core/tokenizer.py
core/transformer.py
core/utils.py
core/vision_encoder/__init__.py
core/vision_encoder/bpe_simple_vocab_16e6.txt.gz
core/vision_encoder/config.py
core/vision_encoder/pe.py
core/vision_encoder/rope.py
core/vision_encoder/tokenizer.py
core/vision_encoder/transforms.py
perception_models_perone-1.0.0.dist-info/licenses/LICENSE.PE
perception_models_perone-1.0.0.dist-info/licenses/LICENSE.PLM
perception_models_perone-1.0.0.dist-info/METADATA
perception_models_perone-1.0.0.dist-info/WHEEL
perception_models_perone-1.0.0.dist-info/top_level.txt
perception_models_perone-1.0.0.dist-info/RECORD
